{
  "1": "в”Ңв”Җв”Җв”Җв”Җв”Җв”Җв”Җв”Җв”Җв”җ\nв”Ӯ         в”Ӯ\nв”Ӯ    в—Ҹ    в”Ӯ\nв”Ӯ         в”Ӯ\nв””в”Җв”Җв”Җв”Җв”Җв”Җв”Җв”Җв”Җв”ҳ",
  "2": "в”Ңв”Җв”Җв”Җв”Җв”Җв”Җв”Җв”Җв”Җв”җ\nв”Ӯ  в—Ҹ      в”Ӯ\nв”Ӯ         в”Ӯ\nв”Ӯ      в—Ҹ  в”Ӯ\nв””в”Җв”Җв”Җв”Җв”Җв”Җв”Җв”Җв”Җв”ҳ",
  "3": "в”Ңв”Җв”Җв”Җв”Җв”Җв”Җв”Җв”Җв”Җв”җ\nв”Ӯ  в—Ҹ      в”Ӯ\nв”Ӯ    в—Ҹ    в”Ӯ\nв”Ӯ      в—Ҹ  в”Ӯ\nв””в”Җв”Җв”Җв”Җв”Җв”Җв”Җв”Җв”Җв”ҳ",
  "4": "в”Ңв”Җв”Җв”Җв”Җв”Җв”Җв”Җв”Җв”Җв”җ\nв”Ӯ  в—Ҹ   в—Ҹ  в”Ӯ\nв”Ӯ         в”Ӯ\nв”Ӯ  в—Ҹ   в—Ҹ  в”Ӯ\nв””в”Җв”Җв”Җв”Җв”Җв”Җв”Җв”Җв”Җв”ҳ",
  "5": "в”Ңв”Җв”Җв”Җв”Җв”Җв”Җв”Җв”Җв”Җв”җ\nв”Ӯ  в—Ҹ   в—Ҹ  в”Ӯ\nв”Ӯ    в—Ҹ    в”Ӯ\nв”Ӯ  в—Ҹ   в—Ҹ  в”Ӯ\nв””в”Җв”Җв”Җв”Җв”Җв”Җв”Җв”Җв”Җв”ҳ",
  "6": "в”Ңв”Җв”Җв”Җв”Җв”Җв”Җв”Җв”Җв”Җв”җ\nв”Ӯ  в—Ҹ   в—Ҹ  в”Ӯ\nв”Ӯ  в—Ҹ   в—Ҹ  в”Ӯ\nв”Ӯ  в—Ҹ   в—Ҹ  в”Ӯ\nв””в”Җв”Җв”Җв”Җв”Җв”Җв”Җв”Җв”Җв”ҳ"
}